concreteproperties/__init__.py
concreteproperties/analysis_section.py
concreteproperties/concrete_section.py
concreteproperties/material.py
concreteproperties/post.py
concreteproperties/pre.py
concreteproperties/prestressed_section.py
concreteproperties/py.typed
concreteproperties/results.py
concreteproperties/stress_strain_profile.py
concreteproperties/utils.py
concreteproperties/design_codes/__init__.py
concreteproperties/design_codes/as3600.py
concreteproperties/design_codes/design_code.py
concreteproperties/design_codes/nzs3101.py
concreteproperties-0.6.4.dist-info/METADATA
concreteproperties-0.6.4.dist-info/WHEEL
concreteproperties-0.6.4.dist-info/licenses/LICENSE
concreteproperties-0.6.4.dist-info/RECORD
