Metadata-Version: 2.3
Name: concreteproperties
Version: 0.6.4
Summary: A python package to determine cross-section propreties of reinforced concrete sections.
Project-URL: Homepage, https://concrete-properties.readthedocs.io
Project-URL: Documentation, https://concrete-properties.readthedocs.io
Project-URL: Repository, https://github.com/robbievanleeuwen/concrete-properties
Project-URL: Issues, https://github.com/robbievanleeuwen/concrete-properties/issues
Project-URL: Changelog, https://github.com/robbievanleeuwen/concrete-properties/releases
Author-email: Robbie van Leeuwen <robbie.vanleeuwen@gmail.com>
Maintainer-email: Robbie van Leeuwen <robbie.vanleeuwen@gmail.com>
License: MIT License
License-File: LICENSE
Keywords: computational-mechanics,concrete,cross-section,finite-element-analysis,post-tensioned-concrete,prestressed-concrete,reinforced-concrete,structural-engineering
Classifier: Development Status :: 4 - Beta
Classifier: Environment :: Console
Classifier: License :: OSI Approved :: MIT License
Classifier: Natural Language :: English
Classifier: Programming Language :: Python :: 3.10
Classifier: Programming Language :: Python :: 3.11
Classifier: Programming Language :: Python :: 3.12
Classifier: Topic :: Scientific/Engineering
Requires-Python: <3.13,>=3.10
Requires-Dist: cytriangle~=1.0.3
Requires-Dist: matplotlib~=3.9.2
Requires-Dist: more-itertools~=10.5.0
Requires-Dist: numpy~=1.26.4
Requires-Dist: rich[jupyter]~=13.9.3
Requires-Dist: scipy~=1.14.1
Requires-Dist: sectionproperties~=3.5.0
Requires-Dist: shapely~=2.0.6
